kappaconfig/__init__.py
kappaconfig/errors.py
kappaconfig/entities/__init__.py
kappaconfig/entities/grammar_tree_nodes.py
kappaconfig/entities/wrappers.py
kappaconfig/functional/__init__.py
kappaconfig/functional/convert.py
kappaconfig/functional/dotlist.py
kappaconfig/functional/load.py
kappaconfig/functional/merge.py
kappaconfig/functional/to_string.py
kappaconfig/functional/unpack_accessors.py
kappaconfig/functional/util.py
kappaconfig/grammar/__init__.py
kappaconfig/grammar/accessor_grammar.py
kappaconfig/grammar/dotlist_grammar.py
kappaconfig/grammar/scalar_grammar.py
kappaconfig/resolvers/__init__.py
kappaconfig/resolvers/default_resolver.py
kappaconfig/resolvers/resolver.py
kappaconfig/resolvers/collection_resolvers/__init__.py
kappaconfig/resolvers/collection_resolvers/collection_resolver.py
kappaconfig/resolvers/collection_resolvers/missing_value_resolver.py
kappaconfig/resolvers/collection_resolvers/template_resolver.py
kappaconfig/resolvers/processors/__init__.py
kappaconfig/resolvers/processors/if_post_processor.py
kappaconfig/resolvers/processors/processor.py
kappaconfig/resolvers/processors/remove_nones_post_processor.py
kappaconfig/resolvers/processors/remove_vars_post_processor.py
kappaconfig/resolvers/scalar_resolvers/__init__.py
kappaconfig/resolvers/scalar_resolvers/env_resolver.py
kappaconfig/resolvers/scalar_resolvers/eval_resolver.py
kappaconfig/resolvers/scalar_resolvers/from_dotlist_resolver.py
kappaconfig/resolvers/scalar_resolvers/interpolation_resolver.py
kappaconfig/resolvers/scalar_resolvers/merge_with_dotlist_resolver.py
kappaconfig/resolvers/scalar_resolvers/nested_yaml_resolver.py
kappaconfig/resolvers/scalar_resolvers/scalar_resolver.py
kappaconfig/resolvers/scalar_resolvers/select_resolver.py
tests_integration/__init__.py
tests_integration/test_complex_yamls.py
tests_integration/test_merge.py
kappaconfig-1.0.31.dist-info/LICENSE
kappaconfig-1.0.31.dist-info/METADATA
kappaconfig-1.0.31.dist-info/WHEEL
kappaconfig-1.0.31.dist-info/top_level.txt
kappaconfig-1.0.31.dist-info/RECORD
