Metadata-Version: 2.1
Name: kappaconfig
Version: 1.0.31
Summary: flexible yaml configuration framework
Home-page: https://github.com/BenediktAlkin/KappaConfig
Project-URL: Source Code, https://github.com/BenediktAlkin/KappaConfig
Project-URL: Bug Tracker, https://github.com/BenediktAlkin/KappaConfig/issues
Classifier: Programming Language :: Python :: 3
Classifier: License :: OSI Approved :: MIT License
Classifier: Operating System :: OS Independent
Requires-Python: >=3.6
License-File: LICENSE
